{
    "Description": {
		"Id": "starsystemdef_Astrokaszy",
		"Name": "Astrokaszy",
		"Details": "Astrokaszy is hot, dry and windswept despite having a large amount of water. Treasure hunters are still drawn to the planet by rumors of a Star League Defense Force cache of precious metals, hidden during the Reunification War.",
        "Icon": ""
    },
    "Tags": {
		"items": [
			"planet_region_marikexpanses",
			"planet_name_astrokaszy",
			"planet_size_medium",
			"planet_climate_arid",
			"planet_feature_moon01",
			"planet_other_moon",
			"planet_pop_small",
			"planet_industry_poor"
		],
		"tagSetSourceFile": ""
    },
    "OwnerID": "Locals",
    "TravelRequirements": [
        {
            "Scope": "Company",
            "RequirementTags": {
                "items": [
                    "map_travel_2"
                ],
                "tagSetSourceFile": ""
            },
            "ExclusionTags": {
                "items": [],
                "tagSetSourceFile": ""
            },
            "RequirementComparisons": []
        }
    ],
    "ContractEmployerIDs": [
		"Locals",
        "Marik",
        "MagistracyOfCanopus",
        "AuriganPirates"
    ],
    "ContractTargetIDs": [
		"Locals",
        "Marik",
        "MagistracyOfCanopus",
        "AuriganPirates"
    ]
}