{
    "Description": {
        "Id": "starsystemdef_RegisRoost_Flipped",
        "Name": "Regis Roost",
        "Details": "Regis Roost is filled with fungal life, in a dizzying array of forms; fungal 'plants', 'fish' and even 'animals' comprise the complex biosphere of the world. Consequently, the air is thick with spores. Visitors are prone to an unpleasant illness known as 'spore-lung'.",
        "Icon": ""
    },
    "contractEmployerIDs": [
        "SyrtisPirates",
        "RenegadePirates",
        "AuriganRestoration",
		"TikonovPirates",
        "CanopianPirates"
    ],
    "contractTargetIDs": [
        "SyrtisPirates",
        "RenegadePirates",
        "AuriganPirates",
        "TaurianConcordat",
		"TikonovPirates",
        "AuriganDirectorate",
        "MagistracyOfCanopus",
        "EvilEye",
        "HarbingersOfDoom"
    ]
}