{
    "id" : "castDef_MarianLeaderDefault",
    "internalName" : "MarianLeaderDefault",
    "firstName" : "Emilius Paulus",
    "lastName" : "Cotta Lothianus",
    "callsign" : "",
    "rank" : "Legatus",
    "gender" : "Male",
    "factionID" : "MarianHegemony",
    "sgCharType" : "UNSET",
    "showRank" : true,
    "showFirstName" : false,
    "showCallsign" : false,
    "showLastName" : true,
    "defaultEmotePortrait" : {
        "emote" : "Default",
        "portraitAssetPath" : "sprites/Portraits/guiTxrPort_backerPiazza_utr.png"
    },
    "emotePotraitList" : [
        
    ]
}
