{
    "Description" : {
        "Id" : "milestone_1282_talk_darkHorse_4",
        "Name" : "conversation",
        "Details" : "Conversations",
        "Icon" : "",
        "Cost" : 0,
        "Rarity" : 0,
        "Purchasable" : false
    },
    "Scope" : "Company",
    "Requirements" : [
        {
            "Scope" : "Company",
            "RequirementTags" : {
                "items" : [],
                "tagSetSourceFile" : ""
            },
            "ExclusionTags" : {
                "items" : null,
                "tagSetSourceFile" : ""
            },
            "RequirementComparisons" : [
                {
                    "obj" : "NextStoryMilestone",
                    "op" : "Equal",
                    "val" : 1282,
                    "valueConstant" : null
                },
				{
                    "obj" : "MissionsComplete",
                    "op" : "GreaterThanOrEqual",
                    "val" : 2,
                    "valueConstant" : null
                }
            ]
        }
    ],
    "Results" : [
        {
            "Scope" : "Company",
            "Requirements" : null,
            "AddedTags" : {},
            "RemovedTags" : {},
            "Stats" : [
				{
					"typeString" : "System.Int32",
                    "name" : "NextStoryMilestone",
                    "value" : 1,
                    "valueConstant" : null
				}
            ],
            "Actions" : [
                {
                    "Type" : "System_StartConversation",
                    "value" : "9cf54229a0472a8d59d7a101",
                    "additionalValues" : [
						"<i>DARK HORSE IV</i>",
						"HPG NEWS"
					]
                }
            ],
            "ForceEvents" : null,
            "TemporaryResult" : false,
            "ResultDuration" : 0
        }
    ],
    "Repeatable" : false
}