{
	"Description": {
		"Id": "starsystemdef_Scheuerheck",
		"Name": "Scheuerheck",
		"Details": "Colonized around 2530 by the Free Worlds League, Scheuerheck found itself in the middle of a power play made by Magistrix Kossandra Centrella, who convinced the planetary governments of Scheuerheck, Ruschegg and Payvand to join her Magistracy Free State. Between 2550 and 2559 all three worlds joined the Canopians but belonged briefly to the Magistracy since they were invaded and reintegrated into the FWL during the Reunification War.",
		"Icon": ""
	},
	"Position": {
		"x": -147.886,
		"y": -328.614,
		"z": 0
	},
	"Tags": {
		"items": [
			"planet_name_scheuerheck",
			"planet_size_large",
			"planet_climate_rocky",
			"planet_pop_medium",
			"planet_faction_marik",
			"planet_civ_periphery",
			"planet_other_battlefield",
			"planet_industry_mining",
			"planet_progress_3"
		],
		"tagSetSourceFile": ""
	},
	"SupportedBiomes": [
        "highlandsSpring",
        "highlandsFall",
        "badlandsParched",
        "tundraFrozen",
        "martianVacuum"
	],
	"MapRequiredTags": {
		"items": [],
		"tagSetSourceFile": ""
	},
	"MapExcludedTags": {
		"items": [],
		"tagSetSourceFile": ""
	},
	"FuelingStation": false,
	"JumpDistance": 4,
	"ownerID": "Marik",
	"ShopRefreshRate": 0,
	"ShopMaxInventory": 0,
	"ShopMaxSpecials": 9,
    "SystemInfluence": [
        {
            "FactionID": "NoFaction",
            "Influence": 0
        },
        {
            "FactionID": "Davion",
            "Influence": 0
        },
        {
            "FactionID": "Liao",
            "Influence": 0
        },
        {
            "FactionID": "Kurita",
            "Influence": 0
        },
        {
            "FactionID": "Marik",
            "Influence": 0
        },
        {
            "FactionID": "Steiner",
            "Influence": 0
        },
        {
            "FactionID": "TaurianConcordat",
            "Influence": 0
        },
        {
            "FactionID": "MagistracyOfCanopus",
            "Influence": 0
        },
        {
            "FactionID": "AuriganDirectorate",
            "Influence": 0
        },
        {
            "FactionID": "AuriganRestoration",
            "Influence": 0
        },
        {
            "FactionID": "ComStar",
            "Influence": 0
        },
        {
            "FactionID": "MercenaryReviewBoard",
            "Influence": 0
        },
        {
            "FactionID": "AuriganPirates",
            "Influence": 0
        },
        {
            "FactionID": "AuriganMercenaries",
            "Influence": 0
        }
    ],
    "TravelRequirements": [
        {
            "Scope": "Company",
            "RequirementTags": {
                "items": [
                    "map_travel_2m"
                ],
                "tagSetSourceFile": ""
            },
            "ExclusionTags": {
                "items": [],
                "tagSetSourceFile": ""
            },
            "RequirementComparisons": []
        }
    ],
	"StarPosition": null,
	"StarType": "K",
	"Depletable": false,
	"UseSystemRoninHiringChance": false,
	"RoninHiringChance": 0,
	"UseMaxContractOverride": false,
	"MaxContractOverride": 0,
	"SystemShopItems": [
		"itemCollection_minor_Marik",
		"itemCollection_shop_mining",
		"itemCollection_shop_battlefield"
	],
	"FactionShopOwnerID": "INVALID_UNSET",
	"FactionShopItems": null,
	"BlackMarketShopItems": null,
	"CoreSystemID": "starsystemdef_Scheuerheck",
	"StartingSystemModes": [
		"KAMEA_CAMPAIGN",
		"CAREER",
		"NONE"
	],
	"DefaultDifficulty": 0,
	"DifficultyList": [
		0,
		8
	],
	"DifficultyModes": [
		"KAMEA_CAMPAIGN",
		"CAREER"
	],
	"ContractEmployerIDs": [
		"Steiner",
		"AuriganPirates",
		"Marik",
		"Liao",
		"MagistracyOfCanopus"
	],
	"ContractTargetIDs": [
		"Steiner",
		"AuriganPirates",
		"Marik",
		"Liao",
		"MagistracyOfCanopus"
	]
}
