{
    "id" : "castDef_IllyrianPirateLeaderDefault",
    "internalName" : "IllyrianPirateLeaderDefault",
    "firstName" : "Ziu",
    "lastName" : "Modelli",
    "callsign" : "",
    "rank" : "Captain",
    "gender" : "Male",
    "factionID" : "IllyrianPirates",
    "sgCharType" : "UNSET",
    "showRank" : true,
    "showFirstName" : true,
    "showCallsign" : false,
    "showLastName" : false,
    "defaultEmotePortrait" : {
        "emote" : "Default",
        "portraitAssetPath" : "sprites/Portraits/guiTxrPort_backerBrewer_utr.png"
    },
    "emotePotraitList" : [
        
    ]
}
