{
    "Description" : {
        "Id" : "fp_StoryTime_HYR_aCountryTooFar",
        "Name" : "A Country Too Far",
        "Details" : "An outer rim world is under threat from unknown raiders who might not be human. Part two of Uncle Chandy's arc.",
        "Icon" : "uixTxrSpot_fp_HyadesRim_Background_6.png"
    },
    "Weight" : 10,
    "InternalName" : "aCountryTooFar",
    "PublishState" : "PUBLISHED",
    "Difficulty" : 4,
    "Requirements" : [
        {
            "Scope" : "Company",
            "RequirementTags" : {
                "items" : [
					"flashpoint_puttingOutAFire_complete",
					"company_story_flashpoints"
				],
                "tagSetSourceFile" : "Tags/CompanyTags"
            },
            "ExclusionTags" : {
                "items" : [],
                "tagSetSourceFile" : ""
            },
            "RequirementComparisons" : []
        }
    ],
    "LocationRequirements" : {
        "Scope" : "StarSystem",
        "RequirementTags" : {
            "items" : [
				"planet_name_coopertown"
            ],
            "tagSetSourceFile" : "Tags/CompanyTags"
        },
        "ExclusionTags" : {
            "items" : [],
            "tagSetSourceFile" : ""
        },
        "RequirementComparisons" : []
    },
    "PotentialEmployers" : [
		"UncleChandy"
    ],
    "TargetFaction" : "YellowBird",
    "AllowRefitTime" : false,
    "FlashpointLength" : "MEDIUM",
    "Repeatable" : true,
    "MilestoneSetID" : "ms_fp_aCountryTooFar",
    "UnitDropTonnageHint" : "",
    "LanceDropTonnageHint" : "",
    "UseAvailableTimeoutOverride" : false,
    "AvailableTimeout" : 0,
    "UseInProgressTimeoutOverride" : false,
    "InProgressTimeout" : 0,
    "RewardCollectionID" : "itemCollection_loot_fp_reward_aCountryTooFar",
    "FlashpointShortDescription" : "Commander, I was attending a local festival of Kuritan kabuki cabaret theatre when local JumpShip issues caused me to become stranded in this system. This has caused all sorts of unforeseen complications and now I can't leave the system due to unfinished business preventing me from leaving, so I require the services of a skilled mercenary company such as yours.",
    "FlashpointDescriberCastDefId" : "castDef_KuritaRepDefault",
    "Tags" : {
        "items" : [
            "BLACKLISTED"
        ],
        "tagSetSourceFile" : "tags/FlashpointTags"
    }
}
